{
"type": "FeatureCollection",
"name": "output_data",
"crs": { "type": "name", "properties": { "name": "urn:ogc:def:crs:EPSG::3857" } },
"features": [
{ "type": "Feature", "properties": { "id": 1, "place": "Tokyo", "latitude": 35.6762, "longitude": 139.6503 }, "geometry": { "type": "Point", "coordinates": [ 139.6503, 35.6762 ] } },
{ "type": "Feature", "properties": { "id": 2, "place": "San Francisco", "latitude": 37.7749, "longitude": -122.4194 }, "geometry": { "type": "Point", "coordinates": [ -122.4194, 37.7749 ] } },
{ "type": "Feature", "properties": { "id": 3, "place": "Jakarta", "latitude": -6.2088, "longitude": 106.8456 }, "geometry": { "type": "Point", "coordinates": [ 106.8456, -6.2088 ] } }
]
}
